ext_message/__init__.py
ext_message-1.0.2.dist-info/LICENSE
ext_message-1.0.2.dist-info/METADATA
ext_message-1.0.2.dist-info/WHEEL
ext_message-1.0.2.dist-info/entry_points.txt
ext_message-1.0.2.dist-info/top_level.txt
ext_message-1.0.2.dist-info/RECORD
