Metadata-Version: 2.1
Name: ext-message
Version: 1.0.2
Home-page: https://github.com/jwjeffr/ext-message
Author: Jacob Jeffries
Author-email: jeffriesjacob0@gmail.com
License-File: LICENSE
Requires-Dist: discord
Requires-Dist: python-dotenv
